lambdapoint/__init__.py
lambdapoint/default_request.py
lambdapoint/execution_type.py
lambdapoint/lambda_mapping.py
lambdapoint/lambda_helper/__init__.py
lambdapoint/lambda_helper/invoke_lambda.py
lambdapoint/lambda_helper/lambda_event_builder.py
lambdapoint-0.1.6.dist-info/METADATA
lambdapoint-0.1.6.dist-info/WHEEL
lambdapoint-0.1.6.dist-info/top_level.txt
lambdapoint-0.1.6.dist-info/RECORD
