Metadata-Version: 2.1
Name: lambdapoint
Version: 0.1.6
Summary: A python wrapper that makes easy to seamlessly change from API to direct lambda invokations.
Home-page: UNKNOWN
Author: Daniel Renteria
License: UNKNOWN
Platform: UNKNOWN
Requires-Dist: boto3
Requires-Dist: requests
